<?xml version="1.0" encoding="utf-8" standalone="yes"?>
<set name="Duel Decks: Elves vs. Goblins" id="9275ae28-1099-4ae2-9a93-15861695521d" gameId="A6C8D2E8-7CD8-11DD-8F94-E62B56D89593" gameVersion="3.3.0.0" version="1.0">
  <cards>
    <card name="Akki Coalflinger" id="e6eb2a03-4983-a3f4-300d-9242b27de7c5">
      <property name="Cost" value="{1}{R}{R}" />
      <property name="CMC" value="3" />
      <property name="Color" value="Red" />
      <property name="Type" value="Creature" />
      <property name="Subtype" value="Goblin Shaman" />
      <property name="Rarity" value="Uncommon" />
      <property name="Rules" value="First strike&#xD;&#xA;{R}, {T}: Attacking creatures gain first strike until end of turn." />
      <property name="Power" value="2" />
      <property name="Toughness" value="2" />
      <property name="PT Box" value="2 / 2" />
      <property name="Artist" value="Nottsuo" />
      <property name="Number" value="033" />
      <property name="Flavor" value="No matter where you find them, goblins love rocks." />
      <property name="MultiverseId" value="159328" />
    </card>
    <card name="Allosaurus Rider" id="f3588b47-07c4-796c-331d-e4e695c2949c">
      <property name="Cost" value="{5}{G}{G}" />
      <property name="CMC" value="7" />
      <property name="Color" value="Green" />
      <property name="Type" value="Creature" />
      <property name="Subtype" value="Elf Warrior" />
      <property name="Rarity" value="Rare" />
      <property name="Rules" value="You may exile two green cards from your hand rather than pay Allosaurus Rider's mana cost.&#xD;&#xA;Allosaurus Rider's power and toughness are each equal to 1 plus the number of lands you control." />
      <property name="Power" value="1+*" />
      <property name="Toughness" value="1+*" />
      <property name="PT Box" value="1+* / 1+*" />
      <property name="Artist" value="Daren Bader" />
      <property name="Number" value="002" />
      <property name="MultiverseId" value="158100" />
    </card>
    <card name="Ambush Commander" id="b24f00e2-1ad3-f003-c4bc-fe9a603f28b0">
      <property name="Cost" value="{3}{G}{G}" />
      <property name="CMC" value="5" />
      <property name="Color" value="Green" />
      <property name="Type" value="Creature" />
      <property name="Subtype" value="Elf" />
      <property name="Rarity" value="Rare" />
      <property name="Rules" value="Forests you control are 1/1 green Elf creatures that are still lands.&#xD;&#xA;{1}{G}, Sacrifice an Elf: Target creature gets +3/+3 until end of turn." />
      <property name="Power" value="2" />
      <property name="Toughness" value="2" />
      <property name="PT Box" value="2 / 2" />
      <property name="Artist" value="Lucio Parrillo" />
      <property name="Number" value="001" />
      <property name="MultiverseId" value="157950" />
    </card>
    <card name="Boggart Shenanigans" id="ef23eb11-95c3-13f1-f16e-ab8dff6acef9">
      <property name="Cost" value="{2}{R}" />
      <property name="CMC" value="3" />
      <property name="Color" value="Red" />
      <property name="Type" value="Tribal Enchantment" />
      <property name="Subtype" value="Goblin" />
      <property name="Rarity" value="Uncommon" />
      <property name="Rules" value="Whenever another Goblin you control is put into a graveyard from the battlefield, you may have Boggart Shenanigans deal 1 damage to target player." />
      <property name="Artist" value="Warren Mahy" />
      <property name="Number" value="054" />
      <property name="Flavor" value="Boggarts revel in discovering new sensations, from the texture of an otter pellet to the squeak of a dying warren mate." />
      <property name="MultiverseId" value="157915" />
    </card>
    <card name="Clickslither" id="50039f8a-f8a6-8ce8-7a62-26760dd1f55f">
      <property name="Cost" value="{1}{R}{R}{R}" />
      <property name="CMC" value="4" />
      <property name="Color" value="Red" />
      <property name="Type" value="Creature" />
      <property name="Subtype" value="Insect" />
      <property name="Rarity" value="Rare" />
      <property name="Rules" value="Haste&#xD;&#xA;Sacrifice a Goblin: Clickslither gets +2/+2 and gains trample until end of turn." />
      <property name="Power" value="3" />
      <property name="Toughness" value="3" />
      <property name="PT Box" value="3 / 3" />
      <property name="Artist" value="Kev Walker" />
      <property name="Number" value="034" />
      <property name="Flavor" value="The least popular goblins get the outer caves." />
      <property name="MultiverseId" value="157928" />
    </card>
    <card name="Elvish Eulogist" id="6ee354be-d654-aa80-f289-d2e8e86d3610">
      <property name="Cost" value="{G}" />
      <property name="CMC" value="1" />
      <property name="Color" value="Green" />
      <property name="Type" value="Creature" />
      <property name="Subtype" value="Elf Shaman" />
      <property name="Rarity" value="Common" />
      <property name="Rules" value="Sacrifice Elvish Eulogist: You gain 1 life for each Elf card in your graveyard." />
      <property name="Power" value="1" />
      <property name="Toughness" value="1" />
      <property name="PT Box" value="1 / 1" />
      <property name="Artist" value="Ben Thompson" />
      <property name="Number" value="003" />
      <property name="Flavor" value="&quot;No matter how adept our artistic skill, our effigies can never hope to capture the vibrant beauty of a living elf. Perhaps that is truly why we mourn.&quot;" />
      <property name="MultiverseId" value="158120" />
    </card>
    <card name="Elvish Harbinger" id="74c5b4ab-29df-d632-2c61-39296bcb857a">
      <property name="Cost" value="{2}{G}" />
      <property name="CMC" value="3" />
      <property name="Color" value="Green" />
      <property name="Type" value="Creature" />
      <property name="Subtype" value="Elf Druid" />
      <property name="Rarity" value="Uncommon" />
      <property name="Rules" value="When Elvish Harbinger enters the battlefield, you may search your library for an Elf card, reveal it, then shuffle your library and put that card on top of it.&#xD;&#xA;{T}: Add one mana of any color to your mana pool." />
      <property name="Power" value="1" />
      <property name="Toughness" value="2" />
      <property name="PT Box" value="1 / 2" />
      <property name="Artist" value="Larry MacDougall" />
      <property name="Number" value="004" />
      <property name="MultiverseId" value="158121" />
    </card>
    <card name="Elvish Promenade" id="f53613d5-ce28-802c-0087-79eb268ad6bb">
      <property name="Cost" value="{3}{G}" />
      <property name="CMC" value="4" />
      <property name="Color" value="Green" />
      <property name="Type" value="Tribal Sorcery" />
      <property name="Subtype" value="Elf" />
      <property name="Rarity" value="Uncommon" />
      <property name="Rules" value="Put a 1/1 green Elf Warrior creature token onto the battlefield for each Elf you control." />
      <property name="Artist" value="Steve Ellis" />
      <property name="Number" value="020" />
      <property name="Flavor" value="The faultless and immaculate castes form the lower tiers of elvish society, with the exquisite caste above them. At the pinnacle is the perfect, a consummate blend of aristocrat and predator." />
      <property name="MultiverseId" value="159030" />
    </card>
    <card name="Elvish Warrior" id="9f04460f-3355-7987-e5d8-5beac5fd4118">
      <property name="Cost" value="{G}{G}" />
      <property name="CMC" value="2" />
      <property name="Color" value="Green" />
      <property name="Type" value="Creature" />
      <property name="Subtype" value="Elf Warrior" />
      <property name="Rarity" value="Common" />
      <property name="Rules" value="" />
      <property name="Power" value="2" />
      <property name="Toughness" value="3" />
      <property name="PT Box" value="2 / 3" />
      <property name="Artist" value="Christopher Moeller" />
      <property name="Number" value="005" />
      <property name="Flavor" value="&quot;My tales of war are the stories most asked for around the fires at night, but they're the ones I care least to tell.&quot;" />
      <property name="MultiverseId" value="158136" />
    </card>
    <card name="Emberwilde Augur" id="8ffb839f-0af2-d2e9-77de-d75e01e23161">
      <property name="Cost" value="{1}{R}" />
      <property name="CMC" value="2" />
      <property name="Color" value="Red" />
      <property name="Type" value="Creature" />
      <property name="Subtype" value="Goblin Shaman" />
      <property name="Rarity" value="Common" />
      <property name="Rules" value="Sacrifice Emberwilde Augur: Emberwilde Augur deals 3 damage to target player. Activate this ability only during your upkeep." />
      <property name="Power" value="2" />
      <property name="Toughness" value="1" />
      <property name="PT Box" value="2 / 1" />
      <property name="Artist" value="Brandon Kitkouski" />
      <property name="Number" value="035" />
      <property name="Flavor" value="Legends say a djinn gave the goblins a gift they could never hope to master." />
      <property name="MultiverseId" value="157932" />
    </card>
    <card name="Flamewave Invoker" id="ff8851a9-4bda-2cea-b1e8-24f32bd80827">
      <property name="Cost" value="{2}{R}" />
      <property name="CMC" value="3" />
      <property name="Color" value="Red" />
      <property name="Type" value="Creature" />
      <property name="Subtype" value="Goblin Mutant" />
      <property name="Rarity" value="Uncommon" />
      <property name="Rules" value="{7}{R}: Flamewave Invoker deals 5 damage to target player." />
      <property name="Power" value="2" />
      <property name="Toughness" value="2" />
      <property name="PT Box" value="2 / 2" />
      <property name="Artist" value="Dave Dorman" />
      <property name="Number" value="036" />
      <property name="Flavor" value="Inside even the humblest goblin lurks the potential for far greater things—and far worse." />
      <property name="MultiverseId" value="159053" />
    </card>
    <card name="Forest" id="47117e40-45ba-33dd-f976-7c1ffbe77401">
      <property name="CMC" value="0" />
      <property name="Color" value="Colorless" />
      <property name="Type" value="Basic Land" />
      <property name="Subtype" value="Forest" />
      <property name="Rarity" value="Basic Land" />
      <property name="Rules" value="G" />
      <property name="Artist" value="John Avon" />
      <property name="Number" value="029" />
      <property name="MultiverseId" value="157948" />
      <property name="Flags" value="G" />
    </card>
    <card name="Forest" id="147df637-8d2f-544c-bea2-0a72ea76bde5">
      <property name="CMC" value="0" />
      <property name="Color" value="Colorless" />
      <property name="Type" value="Basic Land" />
      <property name="Subtype" value="Forest" />
      <property name="Rarity" value="Basic Land" />
      <property name="Rules" value="G" />
      <property name="Artist" value="Glen Angus" />
      <property name="Number" value="028" />
      <property name="MultiverseId" value="157946" />
      <property name="Flags" value="G" />
    </card>
    <card name="Forest" id="019e57aa-5f8a-13f5-438d-2a1a424acc3a">
      <property name="CMC" value="0" />
      <property name="Color" value="Colorless" />
      <property name="Type" value="Basic Land" />
      <property name="Subtype" value="Forest" />
      <property name="Rarity" value="Basic Land" />
      <property name="Rules" value="G" />
      <property name="Artist" value="Rob Alexander" />
      <property name="Number" value="031" />
      <property name="MultiverseId" value="159041" />
      <property name="Flags" value="G" />
    </card>
    <card name="Forest" id="593c1bf6-77d0-0d80-9249-2f6e9fc48daa">
      <property name="CMC" value="0" />
      <property name="Color" value="Colorless" />
      <property name="Type" value="Basic Land" />
      <property name="Subtype" value="Forest" />
      <property name="Rarity" value="Basic Land" />
      <property name="Rules" value="G" />
      <property name="Artist" value="John Avon" />
      <property name="Number" value="030" />
      <property name="MultiverseId" value="159042" />
      <property name="Flags" value="G" />
    </card>
    <card name="Forgotten Cave" id="dc11146c-32db-966c-7b1a-6780e6b3d9ee">
      <property name="CMC" value="0" />
      <property name="Color" value="Colorless" />
      <property name="Type" value="Land" />
      <property name="Rarity" value="Common" />
      <property name="Rules" value="Forgotten Cave enters the battlefield tapped.&#xD;&#xA;{T}: Add {R} to your mana pool.&#xD;&#xA;Cycling {R} ({R}, Discard this card: Draw a card.)" />
      <property name="Artist" value="Tony Szczudlo" />
      <property name="Number" value="057" />
      <property name="MultiverseId" value="159327" />
      <property name="Flags" value="R" />
    </card>
    <card name="Gempalm Incinerator" id="6133752e-05a3-4860-2ce6-2b7d662758c0">
      <property name="Cost" value="{2}{R}" />
      <property name="CMC" value="3" />
      <property name="Color" value="Red" />
      <property name="Type" value="Creature" />
      <property name="Subtype" value="Goblin" />
      <property name="Rarity" value="Uncommon" />
      <property name="Rules" value="Cycling {1}{R} ({1}{R}, Discard this card: Draw a card.)&#xD;&#xA;When you cycle Gempalm Incinerator, you may have it deal X damage to target creature, where X is the number of Goblins on the battlefield." />
      <property name="Power" value="2" />
      <property name="Toughness" value="1" />
      <property name="PT Box" value="2 / 1" />
      <property name="Artist" value="Luca Zontini" />
      <property name="Number" value="037" />
      <property name="MultiverseId" value="157929" />
    </card>
    <card name="Gempalm Strider" id="b5f3ca80-a1f0-834d-7e69-146c213a2ca1">
      <property name="Cost" value="{1}{G}" />
      <property name="CMC" value="2" />
      <property name="Color" value="Green" />
      <property name="Type" value="Creature" />
      <property name="Subtype" value="Elf" />
      <property name="Rarity" value="Uncommon" />
      <property name="Rules" value="Cycling {2}{G}{G} ({2}{G}{G}, Discard this card: Draw a card.)&#xD;&#xA;When you cycle Gempalm Strider, Elf creatures get +2/+2 until end of turn." />
      <property name="Power" value="2" />
      <property name="Toughness" value="2" />
      <property name="PT Box" value="2 / 2" />
      <property name="Artist" value="Tim Hildebrandt" />
      <property name="Number" value="006" />
      <property name="MultiverseId" value="158117" />
    </card>
    <card name="Giant Growth" id="855bbee4-c894-477a-db75-5cc11d50ff48">
      <property name="Cost" value="{G}" />
      <property name="CMC" value="1" />
      <property name="Color" value="Green" />
      <property name="Type" value="Instant" />
      <property name="Rarity" value="Common" />
      <property name="Rules" value="Target creature gets +3/+3 until end of turn." />
      <property name="Artist" value="Matt Cavotta" />
      <property name="Number" value="021" />
      <property name="MultiverseId" value="159037" />
    </card>
    <card name="Goblin Burrows" id="d142cbbd-e4ce-59eb-956d-c263bcc0a50e">
      <property name="CMC" value="0" />
      <property name="Color" value="Colorless" />
      <property name="Type" value="Land" />
      <property name="Rarity" value="Uncommon" />
      <property name="Rules" value="{T}: Add {C} to your mana pool.&#xD;&#xA;{1}{R}, {T}: Target Goblin creature gets +2/+0 until end of turn." />
      <property name="Artist" value="David Martin" />
      <property name="Number" value="058" />
      <property name="MultiverseId" value="157935" />
    </card>
    <card name="Goblin Cohort" id="04d32e69-3454-ccc1-eece-8b7386942cec">
      <property name="Cost" value="{R}" />
      <property name="CMC" value="1" />
      <property name="Color" value="Red" />
      <property name="Type" value="Creature" />
      <property name="Subtype" value="Goblin Warrior" />
      <property name="Rarity" value="Common" />
      <property name="Rules" value="Goblin Cohort can't attack unless you've cast a creature spell this turn." />
      <property name="Power" value="2" />
      <property name="Toughness" value="2" />
      <property name="PT Box" value="2 / 2" />
      <property name="Artist" value="Darrell Riche" />
      <property name="Number" value="038" />
      <property name="Flavor" value="Akki shells provided good protection when downhill charging became headlong tumbling." />
      <property name="MultiverseId" value="157922" />
    </card>
    <card name="Goblin Matron" id="854cb95f-60db-327c-7318-a4f1bdbc67bc">
      <property name="Cost" value="{2}{R}" />
      <property name="CMC" value="3" />
      <property name="Color" value="Red" />
      <property name="Type" value="Creature" />
      <property name="Subtype" value="Goblin" />
      <property name="Rarity" value="Uncommon" />
      <property name="Rules" value="When Goblin Matron enters the battlefield, you may search your library for a Goblin card, reveal that card, and put it into your hand. If you do, shuffle your library." />
      <property name="Power" value="1" />
      <property name="Toughness" value="1" />
      <property name="PT Box" value="1 / 1" />
      <property name="Artist" value="Daniel Gelon" />
      <property name="Number" value="039" />
      <property name="Flavor" value="There's always room for one more." />
      <property name="MultiverseId" value="157933" />
    </card>
    <card name="Goblin Ringleader" id="b20cc6d4-3c2e-57b5-9b95-0b8e589590cb">
      <property name="Cost" value="{3}{R}" />
      <property name="CMC" value="4" />
      <property name="Color" value="Red" />
      <property name="Type" value="Creature" />
      <property name="Subtype" value="Goblin" />
      <property name="Rarity" value="Uncommon" />
      <property name="Rules" value="Haste&#xD;&#xA;When Goblin Ringleader enters the battlefield, reveal the top four cards of your library. Put all Goblin cards revealed this way into your hand and the rest on the bottom of your library in any order." />
      <property name="Power" value="2" />
      <property name="Toughness" value="2" />
      <property name="PT Box" value="2 / 2" />
      <property name="Artist" value="Mark Romanoski" />
      <property name="Number" value="040" />
      <property name="MultiverseId" value="157937" />
    </card>
    <card name="Goblin Sledder" id="5c58a45f-8e09-f6d7-bd0d-b85f0dd086a0">
      <property name="Cost" value="{R}" />
      <property name="CMC" value="1" />
      <property name="Color" value="Red" />
      <property name="Type" value="Creature" />
      <property name="Subtype" value="Goblin" />
      <property name="Rarity" value="Common" />
      <property name="Rules" value="Sacrifice a Goblin: Target creature gets +1/+1 until end of turn." />
      <property name="Power" value="1" />
      <property name="Toughness" value="1" />
      <property name="PT Box" value="1 / 1" />
      <property name="Artist" value="Ron Spencer" />
      <property name="Number" value="041" />
      <property name="Flavor" value="&quot;Let's play ‘sled.' Here's how it works: you're the sled.&quot;" />
      <property name="MultiverseId" value="159049" />
    </card>
    <card name="Goblin Warchief" id="e75b11e8-a7de-a305-99b0-ccf5c34a866a">
      <property name="Cost" value="{1}{R}{R}" />
      <property name="CMC" value="3" />
      <property name="Color" value="Red" />
      <property name="Type" value="Creature" />
      <property name="Subtype" value="Goblin Warrior" />
      <property name="Rarity" value="Uncommon" />
      <property name="Rules" value="Goblin spells you cast cost {1} less to cast.&#xD;&#xA;Goblin creatures you control have haste." />
      <property name="Power" value="2" />
      <property name="Toughness" value="2" />
      <property name="PT Box" value="2 / 2" />
      <property name="Artist" value="Greg &amp; Tim Hildebrandt" />
      <property name="Number" value="042" />
      <property name="Flavor" value="They poured from the Skirk Ridge like lava, burning and devouring everything in their path." />
      <property name="MultiverseId" value="157934" />
    </card>
    <card name="Harmonize" id="5cde83c3-3789-55b4-8545-a3d84c7ec197">
      <property name="Cost" value="{2}{G}{G}" />
      <property name="CMC" value="4" />
      <property name="Color" value="Green" />
      <property name="Type" value="Sorcery" />
      <property name="Rarity" value="Uncommon" />
      <property name="Rules" value="Draw three cards." />
      <property name="Artist" value="Rob Alexander" />
      <property name="Number" value="022" />
      <property name="Flavor" value="&quot;Life's greatest lessons don't come from focus or concentration. They come from breathing and simply noticing.&quot;—Seton, centaur druid" />
      <property name="MultiverseId" value="159033" />
    </card>
    <card name="Heedless One" id="c4a20e4d-1f53-ed35-aac8-579a7a43355b">
      <property name="Cost" value="{3}{G}" />
      <property name="CMC" value="4" />
      <property name="Color" value="Green" />
      <property name="Type" value="Creature" />
      <property name="Subtype" value="Elf Avatar" />
      <property name="Rarity" value="Uncommon" />
      <property name="Rules" value="Trample&#xD;&#xA;Heedless One's power and toughness are each equal to the number of Elves on the battlefield." />
      <property name="Power" value="*" />
      <property name="Toughness" value="*" />
      <property name="PT Box" value="* / *" />
      <property name="Artist" value="Mark Zug" />
      <property name="Number" value="007" />
      <property name="Flavor" value="&quot;Channel your vitality through me.&quot;" />
      <property name="MultiverseId" value="158113" />
    </card>
    <card name="Ib Halfheart, Goblin Tactician" id="17fa1d05-799a-ae90-98ca-abf8d549b4b5">
      <property name="Cost" value="{3}{R}" />
      <property name="CMC" value="4" />
      <property name="Color" value="Red" />
      <property name="Type" value="Legendary Creature" />
      <property name="Subtype" value="Goblin Advisor" />
      <property name="Rarity" value="Rare" />
      <property name="Rules" value="Whenever another Goblin you control becomes blocked, sacrifice it. If you do, it deals 4 damage to each creature blocking it.&#xD;&#xA;Sacrifice two Mountains: Put two 1/1 red Goblin creature tokens onto the battlefield." />
      <property name="Power" value="3" />
      <property name="Toughness" value="2" />
      <property name="PT Box" value="3 / 2" />
      <property name="Artist" value="Wayne Reynolds" />
      <property name="Number" value="043" />
      <property name="Flavor" value="&quot;Everybody but me—CHARGE!&quot;" />
      <property name="MultiverseId" value="157923" />
    </card>
    <card name="Imperious Perfect" id="e1e48066-1a24-e27b-3118-d189387a95f2">
      <property name="Cost" value="{2}{G}" />
      <property name="CMC" value="3" />
      <property name="Color" value="Green" />
      <property name="Type" value="Creature" />
      <property name="Subtype" value="Elf Warrior" />
      <property name="Rarity" value="Uncommon" />
      <property name="Rules" value="Other Elf creatures you control get +1/+1.&#xD;&#xA;{G}, {T}: Put a 1/1 green Elf Warrior creature token onto the battlefield." />
      <property name="Power" value="2" />
      <property name="Toughness" value="2" />
      <property name="PT Box" value="2 / 2" />
      <property name="Artist" value="Scott M. Fischer" />
      <property name="Number" value="008" />
      <property name="Flavor" value="In a culture of beauty, the most beautiful are worshipped as gods." />
      <property name="MultiverseId" value="158123" />
    </card>
    <card name="Llanowar Elves" id="59c2afd9-021f-ca3d-5f98-174931967e6b">
      <property name="Cost" value="{G}" />
      <property name="CMC" value="1" />
      <property name="Color" value="Green" />
      <property name="Type" value="Creature" />
      <property name="Subtype" value="Elf Druid" />
      <property name="Rarity" value="Common" />
      <property name="Rules" value="{T}: Add {G} to your mana pool." />
      <property name="Power" value="1" />
      <property name="Toughness" value="1" />
      <property name="PT Box" value="1 / 1" />
      <property name="Artist" value="Kev Walker" />
      <property name="Number" value="009" />
      <property name="Flavor" value="One bone broken for every twig snapped underfoot.—Llanowar penalty for trespassing" />
      <property name="MultiverseId" value="158112" />
    </card>
    <card name="Lys Alana Huntmaster" id="71b2eda5-8102-4c7f-b0e1-9c67b38844b7">
      <property name="Cost" value="{2}{G}{G}" />
      <property name="CMC" value="4" />
      <property name="Color" value="Green" />
      <property name="Type" value="Creature" />
      <property name="Subtype" value="Elf Warrior" />
      <property name="Rarity" value="Common" />
      <property name="Rules" value="Whenever you cast an Elf spell, you may put a 1/1 green Elf Warrior creature token onto the battlefield." />
      <property name="Power" value="3" />
      <property name="Toughness" value="3" />
      <property name="PT Box" value="3 / 3" />
      <property name="Artist" value="Pete Venters" />
      <property name="Number" value="010" />
      <property name="Flavor" value="From the highest tiers of Dawn's Light Palace to the deepest shade of Wren's Run, the silver notes of the horn shimmer through the air, and all who hear it feel its pull." />
      <property name="MultiverseId" value="158125" />
    </card>
    <card name="Mogg Fanatic" id="16b8fa15-f383-9d03-e4f1-04234992439b">
      <property name="Cost" value="{R}" />
      <property name="CMC" value="1" />
      <property name="Color" value="Red" />
      <property name="Type" value="Creature" />
      <property name="Subtype" value="Goblin" />
      <property name="Rarity" value="Uncommon" />
      <property name="Rules" value="Sacrifice Mogg Fanatic: Mogg Fanatic deals 1 damage to target creature or player." />
      <property name="Power" value="1" />
      <property name="Toughness" value="1" />
      <property name="PT Box" value="1 / 1" />
      <property name="Artist" value="Brom" />
      <property name="Number" value="044" />
      <property name="Flavor" value="&quot;I got it! I got it! I—&quot;" />
      <property name="MultiverseId" value="157925" />
    </card>
    <card name="Mogg War Marshal" id="bcc5aba4-8221-7738-c2c2-c8d46c5cadd8">
      <property name="Cost" value="{1}{R}" />
      <property name="CMC" value="2" />
      <property name="Color" value="Red" />
      <property name="Type" value="Creature" />
      <property name="Subtype" value="Goblin Warrior" />
      <property name="Rarity" value="Common" />
      <property name="Rules" value="Echo {1}{R} (At the beginning of your upkeep, if this came under your control since the beginning of your last upkeep, sacrifice it unless you pay its echo cost.)&#xD;&#xA;When Mogg War Marshal enters the battlefield or dies, put a 1/1 red Goblin creature token onto the battlefield." />
      <property name="Power" value="1" />
      <property name="Toughness" value="1" />
      <property name="PT Box" value="1 / 1" />
      <property name="Artist" value="Wayne England" />
      <property name="Number" value="045" />
      <property name="MultiverseId" value="157924" />
    </card>
    <card name="Moonglove Extract" id="a6c38cc0-93e2-7509-9460-057053319201">
      <property name="Cost" value="{3}" />
      <property name="CMC" value="3" />
      <property name="Color" value="Colorless" />
      <property name="Type" value="Artifact" />
      <property name="Rarity" value="Common" />
      <property name="Rules" value="Sacrifice Moonglove Extract: Moonglove Extract deals 2 damage to target creature or player." />
      <property name="Artist" value="Terese Nielsen" />
      <property name="Number" value="024" />
      <property name="Flavor" value="Diluted, moonglove can etch living tissue. Concentrated, a drop will kill a giant." />
      <property name="MultiverseId" value="159032" />
    </card>
    <card name="Mountain" id="f3926b12-3a58-fb29-bde9-1b8c9446ac1a">
      <property name="CMC" value="0" />
      <property name="Color" value="Colorless" />
      <property name="Type" value="Basic Land" />
      <property name="Subtype" value="Mountain" />
      <property name="Rarity" value="Basic Land" />
      <property name="Rules" value="R" />
      <property name="Artist" value="Sam Wood" />
      <property name="Number" value="062" />
      <property name="MultiverseId" value="157941" />
      <property name="Flags" value="R" />
    </card>
    <card name="Mountain" id="24afe0ad-1fe4-1611-f6b7-c47ada1606a2">
      <property name="CMC" value="0" />
      <property name="Color" value="Colorless" />
      <property name="Type" value="Basic Land" />
      <property name="Subtype" value="Mountain" />
      <property name="Rarity" value="Basic Land" />
      <property name="Rules" value="R" />
      <property name="Artist" value="Rob Alexander" />
      <property name="Number" value="061" />
      <property name="MultiverseId" value="157939" />
      <property name="Flags" value="R" />
    </card>
    <card name="Mountain" id="bb2bb436-45d5-fd2d-ae8b-cabe09e7df42">
      <property name="CMC" value="0" />
      <property name="Color" value="Colorless" />
      <property name="Type" value="Basic Land" />
      <property name="Subtype" value="Mountain" />
      <property name="Rarity" value="Basic Land" />
      <property name="Rules" value="R" />
      <property name="Artist" value="Jeff Miracola" />
      <property name="Number" value="060" />
      <property name="MultiverseId" value="159061" />
      <property name="Flags" value="R" />
    </card>
    <card name="Mountain" id="99ead4cb-7f9f-82f1-ce1e-06ebf1e7d6a5">
      <property name="CMC" value="0" />
      <property name="Color" value="Colorless" />
      <property name="Type" value="Basic Land" />
      <property name="Subtype" value="Mountain" />
      <property name="Rarity" value="Basic Land" />
      <property name="Rules" value="R" />
      <property name="Artist" value="David Day" />
      <property name="Number" value="059" />
      <property name="MultiverseId" value="157940" />
      <property name="Flags" value="R" />
    </card>
    <card name="Mudbutton Torchrunner" id="6b5bd724-2be9-fc6a-5303-589b98012bbe">
      <property name="Cost" value="{2}{R}" />
      <property name="CMC" value="3" />
      <property name="Color" value="Red" />
      <property name="Type" value="Creature" />
      <property name="Subtype" value="Goblin Warrior" />
      <property name="Rarity" value="Common" />
      <property name="Rules" value="When Mudbutton Torchrunner dies, it deals 3 damage to target creature or player." />
      <property name="Power" value="1" />
      <property name="Toughness" value="1" />
      <property name="PT Box" value="1 / 1" />
      <property name="Artist" value="Steve Ellis" />
      <property name="Number" value="046" />
      <property name="Flavor" value="The oil sloshes against his skull as he nears his destination: the Frogtosser Games and the lighting of the Flaming Boggart." />
      <property name="MultiverseId" value="157919" />
    </card>
    <card name="Raging Goblin" id="12324507-97f4-3e55-c454-af7cf9245f4f">
      <property name="Cost" value="{R}" />
      <property name="CMC" value="1" />
      <property name="Color" value="Red" />
      <property name="Type" value="Creature" />
      <property name="Subtype" value="Goblin Berserker" />
      <property name="Rarity" value="Common" />
      <property name="Rules" value="Haste (This creature can attack and {T} as soon as it comes under your control.)" />
      <property name="Power" value="1" />
      <property name="Toughness" value="1" />
      <property name="PT Box" value="1 / 1" />
      <property name="Artist" value="Jeff Miracola" />
      <property name="Number" value="047" />
      <property name="Flavor" value="He raged at the world, at his family, at his life. But mostly he just raged." />
      <property name="MultiverseId" value="159326" />
    </card>
    <card name="Reckless One" id="3eef5006-c1a1-8997-825c-4671608c6794">
      <property name="Cost" value="{3}{R}" />
      <property name="CMC" value="4" />
      <property name="Color" value="Red" />
      <property name="Type" value="Creature" />
      <property name="Subtype" value="Goblin Avatar" />
      <property name="Rarity" value="Uncommon" />
      <property name="Rules" value="Haste&#xD;&#xA;Reckless One's power and toughness are each equal to the number of Goblins on the battlefield." />
      <property name="Power" value="*" />
      <property name="Toughness" value="*" />
      <property name="PT Box" value="* / *" />
      <property name="Artist" value="Ron Spencer" />
      <property name="Number" value="048" />
      <property name="Flavor" value="&quot;Release chaos with me!&quot;" />
      <property name="MultiverseId" value="159050" />
    </card>
    <card name="Siege-Gang Commander" id="e6f6d61f-4abd-2600-57a0-910ebee2bac9">
      <property name="Cost" value="{3}{R}{R}" />
      <property name="CMC" value="5" />
      <property name="Color" value="Red" />
      <property name="Type" value="Creature" />
      <property name="Subtype" value="Goblin" />
      <property name="Rarity" value="Rare" />
      <property name="Rules" value="When Siege-Gang Commander enters the battlefield, put three 1/1 red Goblin creature tokens onto the battlefield.&#xD;&#xA;{1}{R}, Sacrifice a Goblin: Siege-Gang Commander deals 2 damage to target creature or player." />
      <property name="Power" value="2" />
      <property name="Toughness" value="2" />
      <property name="PT Box" value="2 / 2" />
      <property name="Artist" value="Lucio Parrillo" />
      <property name="Number" value="032" />
      <property name="MultiverseId" value="157926" />
    </card>
    <card name="Skirk Drill Sergeant" id="b7db93f4-6acb-070e-ff6c-2ac76839cd4e">
      <property name="Cost" value="{1}{R}" />
      <property name="CMC" value="2" />
      <property name="Color" value="Red" />
      <property name="Type" value="Creature" />
      <property name="Subtype" value="Goblin" />
      <property name="Rarity" value="Uncommon" />
      <property name="Rules" value="Whenever Skirk Drill Sergeant or another Goblin dies, you may pay {2}{R}. If you do, reveal the top card of your library. If it's a Goblin permanent card, put it onto the battlefield. Otherwise, put it into your graveyard." />
      <property name="Power" value="2" />
      <property name="Toughness" value="1" />
      <property name="PT Box" value="2 / 1" />
      <property name="Artist" value="Alex Horley-Orlandelli" />
      <property name="Number" value="049" />
      <property name="Flavor" value="&quot;I order you to volunteer.&quot;" />
      <property name="MultiverseId" value="157931" />
    </card>
    <card name="Skirk Fire Marshal" id="8a273eae-6f5a-ae81-b2f6-6b8d7cd000e2">
      <property name="Cost" value="{3}{R}{R}" />
      <property name="CMC" value="5" />
      <property name="Color" value="Red" />
      <property name="Type" value="Creature" />
      <property name="Subtype" value="Goblin" />
      <property name="Rarity" value="Rare" />
      <property name="Rules" value="Protection from red&#xD;&#xA;Tap five untapped Goblins you control: Skirk Fire Marshal deals 10 damage to each creature and each player." />
      <property name="Power" value="2" />
      <property name="Toughness" value="2" />
      <property name="PT Box" value="2 / 2" />
      <property name="Artist" value="Greg &amp; Tim Hildebrandt" />
      <property name="Number" value="050" />
      <property name="Flavor" value="He's boss because he's smart enough to get out of the way." />
      <property name="MultiverseId" value="157936" />
    </card>
    <card name="Skirk Prospector" id="e4ee7ee1-8a2b-c040-57fa-9eeff179e433">
      <property name="Cost" value="{R}" />
      <property name="CMC" value="1" />
      <property name="Color" value="Red" />
      <property name="Type" value="Creature" />
      <property name="Subtype" value="Goblin" />
      <property name="Rarity" value="Common" />
      <property name="Rules" value="Sacrifice a Goblin: Add {R} to your mana pool." />
      <property name="Power" value="1" />
      <property name="Toughness" value="1" />
      <property name="PT Box" value="1 / 1" />
      <property name="Artist" value="Doug Chaffee" />
      <property name="Number" value="051" />
      <property name="Flavor" value="&quot;I like goblins. They make funny little popping sounds when they die.&quot;—Braids, dementia summoner" />
      <property name="MultiverseId" value="159051" />
    </card>
    <card name="Skirk Shaman" id="b6d7cf86-f92f-2b5f-2c34-643fa215ef00">
      <property name="Cost" value="{1}{R}{R}" />
      <property name="CMC" value="3" />
      <property name="Color" value="Red" />
      <property name="Type" value="Creature" />
      <property name="Subtype" value="Goblin Shaman" />
      <property name="Rarity" value="Common" />
      <property name="Rules" value="Skirk Shaman can't be blocked except by artifact creatures and/or red creatures." />
      <property name="Power" value="2" />
      <property name="Toughness" value="2" />
      <property name="PT Box" value="2 / 2" />
      <property name="Artist" value="Chippy" />
      <property name="Number" value="052" />
      <property name="Flavor" value="In a shaman's grimy hands, a concoction of dried Skirk Ridge herbs can become the face of panic." />
      <property name="MultiverseId" value="159055" />
    </card>
    <card name="Slate of Ancestry" id="901d3537-caa7-b483-169d-01fc20d62ea6">
      <property name="Cost" value="{4}" />
      <property name="CMC" value="4" />
      <property name="Color" value="Colorless" />
      <property name="Type" value="Artifact" />
      <property name="Rarity" value="Rare" />
      <property name="Rules" value="{4}, {T}, Discard your hand: Draw a card for each creature you control." />
      <property name="Artist" value="Corey D. Macourek" />
      <property name="Number" value="025" />
      <property name="Flavor" value="The pattern of life can be studied like a book, if you know how to read it." />
      <property name="MultiverseId" value="159501" />
    </card>
    <card name="Spitting Earth" id="7fa8d6fa-8fb0-e4b2-f9fe-02fba6adca2e">
      <property name="Cost" value="{1}{R}" />
      <property name="CMC" value="2" />
      <property name="Color" value="Red" />
      <property name="Type" value="Sorcery" />
      <property name="Rarity" value="Common" />
      <property name="Rules" value="Spitting Earth deals damage to target creature equal to the number of Mountains you control." />
      <property name="Artist" value="Michael Koelsch" />
      <property name="Number" value="055" />
      <property name="Flavor" value="&quot;Within each of you is the strength of a landslide.&quot;—Kumano, to his pupils" />
      <property name="MultiverseId" value="159054" />
    </card>
    <card name="Stonewood Invoker" id="a391928b-ca23-7576-8550-4cba0caf7cf5">
      <property name="Cost" value="{1}{G}" />
      <property name="CMC" value="2" />
      <property name="Color" value="Green" />
      <property name="Type" value="Creature" />
      <property name="Subtype" value="Elf Mutant" />
      <property name="Rarity" value="Common" />
      <property name="Rules" value="{7}{G}: Stonewood Invoker gets +5/+5 until end of turn." />
      <property name="Power" value="2" />
      <property name="Toughness" value="2" />
      <property name="PT Box" value="2 / 2" />
      <property name="Artist" value="Eric Peterson" />
      <property name="Number" value="011" />
      <property name="Flavor" value="The Mirari pulses in his veins." />
      <property name="MultiverseId" value="159324" />
    </card>
    <card name="Sylvan Messenger" id="051dbb00-b86b-c194-193c-db921aa11e9f">
      <property name="Cost" value="{3}{G}" />
      <property name="CMC" value="4" />
      <property name="Color" value="Green" />
      <property name="Type" value="Creature" />
      <property name="Subtype" value="Elf" />
      <property name="Rarity" value="Uncommon" />
      <property name="Rules" value="Trample (This creature can deal excess combat damage to defending player or planeswalker while attacking.)&#xD;&#xA;When Sylvan Messenger enters the battlefield, reveal the top four cards of your library. Put all Elf cards revealed this way into your hand and the rest on the bottom of your library in any order." />
      <property name="Power" value="2" />
      <property name="Toughness" value="2" />
      <property name="PT Box" value="2 / 2" />
      <property name="Artist" value="Heather Hudson" />
      <property name="Number" value="012" />
      <property name="MultiverseId" value="159035" />
    </card>
    <card name="Tar Pitcher" id="e2f9574e-b0ff-bd39-6d43-637ac4f40ebb">
      <property name="Cost" value="{3}{R}" />
      <property name="CMC" value="4" />
      <property name="Color" value="Red" />
      <property name="Type" value="Creature" />
      <property name="Subtype" value="Goblin Shaman" />
      <property name="Rarity" value="Uncommon" />
      <property name="Rules" value="{T}, Sacrifice a Goblin: Tar Pitcher deals 2 damage to target creature or player." />
      <property name="Power" value="2" />
      <property name="Toughness" value="2" />
      <property name="PT Box" value="2 / 2" />
      <property name="Artist" value="Omar Rayyan" />
      <property name="Number" value="053" />
      <property name="Flavor" value="&quot;Auntie Grub had caught a goat, a bleating doe that still squirmed in her arms. At the same time, her warren decided to share with her a sensory greeting of hot tar . . . .&quot;—A tale of Auntie Grub" />
      <property name="MultiverseId" value="157920" />
    </card>
    <card name="Tarfire" id="73095466-eb87-6b31-a19d-27632c9aeb1d">
      <property name="Cost" value="{R}" />
      <property name="CMC" value="1" />
      <property name="Color" value="Red" />
      <property name="Type" value="Tribal Instant" />
      <property name="Subtype" value="Goblin" />
      <property name="Rarity" value="Common" />
      <property name="Rules" value="Tarfire deals 2 damage to target creature or player." />
      <property name="Artist" value="Omar Rayyan" />
      <property name="Number" value="056" />
      <property name="Flavor" value="&quot;After Auntie brushed the soot from her eyes, she discovered something wonderful: the fire had turned the goat into something that smelled delicious.&quot;—A tale of Auntie Grub" />
      <property name="MultiverseId" value="157921" />
    </card>
    <card name="Timberwatch Elf" id="eb380cad-d68e-5c5b-e6a8-07cfaec4e2c8">
      <property name="Cost" value="{2}{G}" />
      <property name="CMC" value="3" />
      <property name="Color" value="Green" />
      <property name="Type" value="Creature" />
      <property name="Subtype" value="Elf" />
      <property name="Rarity" value="Common" />
      <property name="Rules" value="{T}: Target creature gets +X/+X until end of turn, where X is the number of Elves on the battlefield." />
      <property name="Power" value="1" />
      <property name="Toughness" value="2" />
      <property name="PT Box" value="1 / 2" />
      <property name="Artist" value="Dave Dorman" />
      <property name="Number" value="013" />
      <property name="Flavor" value="Even through the Mirari's voice, the elves still hear the call of their kinship." />
      <property name="MultiverseId" value="158118" />
    </card>
    <card name="Tranquil Thicket" id="dabc4492-b402-2ec7-2d83-4f1659c4dc66">
      <property name="CMC" value="0" />
      <property name="Color" value="Colorless" />
      <property name="Type" value="Land" />
      <property name="Rarity" value="Common" />
      <property name="Rules" value="Tranquil Thicket enters the battlefield tapped.&#xD;&#xA;{T}: Add {G} to your mana pool.&#xD;&#xA;Cycling {G} ({G}, Discard this card: Draw a card.)" />
      <property name="Artist" value="Heather Hudson" />
      <property name="Number" value="027" />
      <property name="MultiverseId" value="159325" />
      <property name="Flags" value="G" />
    </card>
    <card name="Voice of the Woods" id="195ca120-8194-e873-b5f6-b4017cd72a15">
      <property name="Cost" value="{3}{G}{G}" />
      <property name="CMC" value="5" />
      <property name="Color" value="Green" />
      <property name="Type" value="Creature" />
      <property name="Subtype" value="Elf" />
      <property name="Rarity" value="Rare" />
      <property name="Rules" value="Tap five untapped Elves you control: Put a 7/7 green Elemental creature token with trample onto the battlefield." />
      <property name="Power" value="2" />
      <property name="Toughness" value="2" />
      <property name="PT Box" value="2 / 2" />
      <property name="Artist" value="Pete Venters" />
      <property name="Number" value="014" />
      <property name="Flavor" value="The ritual of making draws upon the elves' memories and pasts. And elves have long memories and ancient pasts." />
      <property name="MultiverseId" value="159029" />
    </card>
    <card name="Wellwisher" id="ff95f499-dbc4-6e75-c214-3ab3140a6d50">
      <property name="Cost" value="{1}{G}" />
      <property name="CMC" value="2" />
      <property name="Color" value="Green" />
      <property name="Type" value="Creature" />
      <property name="Subtype" value="Elf" />
      <property name="Rarity" value="Common" />
      <property name="Rules" value="{T}: You gain 1 life for each Elf on the battlefield." />
      <property name="Power" value="1" />
      <property name="Toughness" value="1" />
      <property name="PT Box" value="1 / 1" />
      <property name="Artist" value="Christopher Rush" />
      <property name="Number" value="015" />
      <property name="Flavor" value="&quot;Close your ears to the voice of greed, and you can turn a gift for one into a gift for many.&quot;" />
      <property name="MultiverseId" value="158109" />
    </card>
    <card name="Wildsize" id="6cbf7078-2d04-acd8-a0bb-f0e1d51161b3">
      <property name="Cost" value="{2}{G}" />
      <property name="CMC" value="3" />
      <property name="Color" value="Green" />
      <property name="Type" value="Instant" />
      <property name="Rarity" value="Common" />
      <property name="Rules" value="Target creature gets +2/+2 and gains trample until end of turn.&#xD;&#xA;Draw a card." />
      <property name="Artist" value="Jim Murray" />
      <property name="Number" value="023" />
      <property name="Flavor" value="Two times the size, four times the smell." />
      <property name="MultiverseId" value="159036" />
    </card>
    <card name="Wirewood Herald" id="34ce02ab-b1e0-8615-5ea0-3a1e8f129348">
      <property name="Cost" value="{1}{G}" />
      <property name="CMC" value="2" />
      <property name="Color" value="Green" />
      <property name="Type" value="Creature" />
      <property name="Subtype" value="Elf" />
      <property name="Rarity" value="Common" />
      <property name="Rules" value="When Wirewood Herald dies, you may search your library for an Elf card, reveal that card, put it into your hand, then shuffle your library." />
      <property name="Power" value="1" />
      <property name="Toughness" value="1" />
      <property name="PT Box" value="1 / 1" />
      <property name="Artist" value="Alex Horley-Orlandelli" />
      <property name="Number" value="016" />
      <property name="Flavor" value="The goblins laughed as the elf ran away, until more came back." />
      <property name="MultiverseId" value="158110" />
    </card>
    <card name="Wirewood Lodge" id="68dd5f7d-949c-8801-1251-7dc0215abdba">
      <property name="CMC" value="0" />
      <property name="Color" value="Colorless" />
      <property name="Type" value="Land" />
      <property name="Rarity" value="Uncommon" />
      <property name="Rules" value="{T}: Add {C} to your mana pool.&#xD;&#xA;{G}, {T}: Untap target Elf." />
      <property name="Artist" value="Anthony S. Waters" />
      <property name="Number" value="026" />
      <property name="MultiverseId" value="158111" />
    </card>
    <card name="Wirewood Symbiote" id="6d7b8562-40f3-3684-69fe-6d062d960638">
      <property name="Cost" value="{G}" />
      <property name="CMC" value="1" />
      <property name="Color" value="Green" />
      <property name="Type" value="Creature" />
      <property name="Subtype" value="Insect" />
      <property name="Rarity" value="Uncommon" />
      <property name="Rules" value="Return an Elf you control to its owner's hand: Untap target creature. Activate this ability only once each turn." />
      <property name="Power" value="1" />
      <property name="Toughness" value="1" />
      <property name="PT Box" value="1 / 1" />
      <property name="Artist" value="Thomas M. Baxa" />
      <property name="Number" value="017" />
      <property name="Flavor" value="It drinks fatigue." />
      <property name="MultiverseId" value="159322" />
    </card>
    <card name="Wood Elves" id="fe4f537c-53ab-c4b7-85c1-5fc44c952245">
      <property name="Cost" value="{2}{G}" />
      <property name="CMC" value="3" />
      <property name="Color" value="Green" />
      <property name="Type" value="Creature" />
      <property name="Subtype" value="Elf Scout" />
      <property name="Rarity" value="Common" />
      <property name="Rules" value="When Wood Elves enters the battlefield, search your library for a Forest card and put that card onto the battlefield. Then shuffle your library." />
      <property name="Power" value="1" />
      <property name="Toughness" value="1" />
      <property name="PT Box" value="1 / 1" />
      <property name="Artist" value="Christopher Moeller" />
      <property name="Number" value="018" />
      <property name="Flavor" value="Every branch a crossroads, every vine a swift steed." />
      <property name="MultiverseId" value="159038" />
    </card>
    <card name="Wren's Run Vanquisher" id="9a8f1b75-06e9-cc03-039c-9d1e8349b360">
      <property name="Cost" value="{1}{G}" />
      <property name="CMC" value="2" />
      <property name="Color" value="Green" />
      <property name="Type" value="Creature" />
      <property name="Subtype" value="Elf Warrior" />
      <property name="Rarity" value="Uncommon" />
      <property name="Rules" value="As an additional cost to cast Wren's Run Vanquisher, reveal an Elf card from your hand or pay {3}.&#xD;&#xA;Deathtouch (Any amount of damage this deals to a creature is enough to destroy it.)" />
      <property name="Power" value="3" />
      <property name="Toughness" value="3" />
      <property name="PT Box" value="3 / 3" />
      <property name="Artist" value="Parente" />
      <property name="Number" value="019" />
      <property name="MultiverseId" value="158129" />
    </card>
  </cards>
</set>